htrace/__init__.py
htrace/__main__.py
htrace-0.3.0.dist-info/entry_points.txt
htrace-0.3.0.dist-info/LICENSE
htrace-0.3.0.dist-info/WHEEL
htrace-0.3.0.dist-info/METADATA
htrace-0.3.0.dist-info/RECORD
