Metadata-Version: 2.1
Name: htrace
Version: 0.3.0
Summary: Tracing HTTP requests over redirects, link headers
Home-page: https://github.com/datadavev/htrace
License: Apache 2.0
Keywords: http,debug,trace
Author: datadavev
Author-email: 605409+datadavev@users.noreply.github.com
Requires-Python: >=3.6,<4.0
Classifier: License :: Other/Proprietary License
Classifier: Programming Language :: Python :: 3
Classifier: Programming Language :: Python :: 3.6
Classifier: Programming Language :: Python :: 3.7
Classifier: Programming Language :: Python :: 3.8
Classifier: Programming Language :: Python :: 3.9
Classifier: Programming Language :: Python :: 3.10
Classifier: Programming Language :: Python :: 3.11
Requires-Dist: click (>=8,<9)
Requires-Dist: dateparser (>=1.0.0,<2.0.0)
Requires-Dist: requests (>=2,<3)
Project-URL: Repository, https://github.com/datadavev/htrace
